LeadsRx/__init__.py
LeadsRx/client.py
LeadsRx/web_request_interfaces.py
LeadsRx_Python_Client-0.0.9.dist-info/LICENSE
LeadsRx_Python_Client-0.0.9.dist-info/METADATA
LeadsRx_Python_Client-0.0.9.dist-info/WHEEL
LeadsRx_Python_Client-0.0.9.dist-info/top_level.txt
LeadsRx_Python_Client-0.0.9.dist-info/RECORD
