Metadata-Version: 2.1
Name: LeadsRx-Python-Client
Version: 0.0.9
Summary: A python client for querying the LeadsRX API. Created in my spare time to help out Semetricals Analytics Team
Home-page: https://github.com/JoshHatfield/LeadsRx-Python-Client
Author: Josh Hatfield
Author-email: jh@semetrical.com
License: UNKNOWN
Project-URL: Bug Tracker, https://github.com/JoshHatfield/LeadsRx-Python-Client/issues
Platform: UNKNOWN
Classifier: Programming Language :: Python :: 3
Classifier: License :: OSI Approved :: GNU General Public License v3 (GPLv3)
Classifier: Operating System :: OS Independent
Requires-Python: >=3.6
License-File: LICENSE
Requires-Dist: requests (>=2.25.1)
Requires-Dist: pandas (>=1.1.5)
